j5gnpuiwerbngpiutbgn0iutb0pfwef/__init__.py
j5gnpuiwerbngpiutbgn0iutb0pfwef-0.0.1.dist-info/METADATA
j5gnpuiwerbngpiutbgn0iutb0pfwef-0.0.1.dist-info/WHEEL
j5gnpuiwerbngpiutbgn0iutb0pfwef-0.0.1.dist-info/top_level.txt
j5gnpuiwerbngpiutbgn0iutb0pfwef-0.0.1.dist-info/RECORD
